[{"game_id":21400003,"team_id":1610612745,"player_id":203477,"opponent_id":1610612747,"period":"f","season":"2014","min":"7:07","fgm":0,"fga":1,"fg3m":0,"fg3a":1,"ftm":2,"fta":2,"oreb":0,"dreb":1,"ast":0,"blk":0,"stl":"0","to":1,"pf":0,"pts":2,"plus_minus":-8},{"game_id":21400012,"team_id":1610612745,"player_id":203477,"opponent_id":1610612762,"period":"f","season":"2014","min":"8:10","fgm":1,"fga":3,"fg3m":1,"fg3a":1,"ftm":0,"fta":0,"oreb":1,"dreb":0,"ast":0,"blk":0,"stl":"0","to":0,"pf":0,"pts":3,"plus_minus":-12},{"game_id":21400034,"team_id":1610612745,"player_id":203477,"opponent_id":1610612738,"period":"f","season":"2014","min":"34:45","fgm":3,"fga":11,"fg3m":3,"fg3a":9,"ftm":0,"fta":2,"oreb":2,"dreb":2,"ast":2,"blk":0,"stl":"2","to":2,"pf":1,"pts":9,"plus_minus":4},{"game_id":21400043,"team_id":1610612745,"player_id":203477,"opponent_id":1610612755,"period":"f","season":"2014","min":"29:36","fgm":5,"fga":11,"fg3m":3,"fg3a":6,"ftm":0,"fta":0,"oreb":1,"dreb":1,"ast":6,"blk":0,"stl":"2","to":3,"pf":5,"pts":13,"plus_minus":14},{"game_id":21400050,"team_id":1610612745,"player_id":203477,"opponent_id":1610612748,"period":"f","season":"2014","min":"14:00","fgm":3,"fga":3,"fg3m":2,"fg3a":2,"ftm":0,"fta":0,"oreb":0,"dreb":0,"ast":0,"blk":0,"stl":"1","to":0,"pf":1,"pts":8,"plus_minus":-6},{"game_id":21400069,"team_id":1610612745,"player_id":203477,"opponent_id":1610612759,"period":"f","season":"2014","min":"26:22","fgm":5,"fga":10,"fg3m":2,"fg3a":4,"ftm":0,"fta":0,"oreb":1,"dreb":1,"ast":1,"blk":0,"stl":"1","to":0,"pf":3,"pts":12,"plus_minus":16},{"game_id":21400087,"team_id":1610612745,"player_id":203477,"opponent_id":1610612744,"period":"f","season":"2014","min":"38:50","fgm":7,"fga":12,"fg3m":3,"fg3a":7,"ftm":4,"fta":4,"oreb":0,"dreb":4,"ast":1,"blk":0,"stl":"1","to":5,"pf":2,"pts":21,"plus_minus":-16},{"game_id":21400117,"team_id":1610612745,"player_id":203477,"opponent_id":1610612750,"period":"f","season":"2014","min":"26:12","fgm":2,"fga":7,"fg3m":0,"fg3a":3,"ftm":1,"fta":2,"oreb":0,"dreb":2,"ast":1,"blk":0,"stl":"0","to":3,"pf":2,"pts":5,"plus_minus":-7},{"game_id":21400127,"team_id":1610612745,"player_id":203477,"opponent_id":1610612755,"period":"f","season":"2014","min":"26:12","fgm":3,"fga":8,"fg3m":3,"fg3a":6,"ftm":0,"fta":0,"oreb":1,"dreb":1,"ast":3,"blk":0,"stl":"0","to":1,"pf":2,"pts":9,"plus_minus":16},{"game_id":21400151,"team_id":1610612745,"player_id":203477,"opponent_id":1610612763,"period":"f","season":"2014","min":"20:52","fgm":3,"fga":9,"fg3m":1,"fg3a":5,"ftm":1,"fta":1,"oreb":0,"dreb":0,"ast":3,"blk":0,"stl":"1","to":1,"pf":2,"pts":8,"plus_minus":1},{"game_id":21400188,"team_id":1610612745,"player_id":203477,"opponent_id":1610612742,"period":"f","season":"2014","min":"2:47","fgm":0,"fga":0,"fg3m":0,"fg3a":0,"ftm":0,"fta":0,"oreb":0,"dreb":0,"ast":0,"blk":0,"stl":"1","to":2,"pf":0,"pts":0,"plus_minus":-3},{"game_id":21400202,"team_id":1610612745,"player_id":203477,"opponent_id":1610612752,"period":"f","season":"2014","min":"26:19","fgm":2,"fga":8,"fg3m":1,"fg3a":5,"ftm":2,"fta":2,"oreb":0,"dreb":0,"ast":3,"blk":0,"stl":"1","to":1,"pf":4,"pts":7,"plus_minus":11},{"game_id":21400217,"team_id":1610612745,"player_id":203477,"opponent_id":1610612758,"period":"f","season":"2014","min":"31:59","fgm":9,"fga":16,"fg3m":6,"fg3a":10,"ftm":0,"fta":0,"oreb":3,"dreb":3,"ast":4,"blk":0,"stl":"4","to":1,"pf":1,"pts":24,"plus_minus":13},{"game_id":21400228,"team_id":1610612745,"player_id":203477,"opponent_id":1610612746,"period":"f","season":"2014","min":"14:55","fgm":4,"fga":8,"fg3m":3,"fg3a":6,"ftm":2,"fta":3,"oreb":0,"dreb":2,"ast":0,"blk":0,"stl":"0","to":0,"pf":1,"pts":13,"plus_minus":3},{"game_id":21400378,"team_id":1610612745,"player_id":203477,"opponent_id":1610612743,"period":"f","season":"2014","min":"6:32","fgm":0,"fga":2,"fg3m":0,"fg3a":1,"ftm":0,"fta":0,"oreb":0,"dreb":0,"ast":0,"blk":0,"stl":"0","to":0,"pf":1,"pts":0,"plus_minus":-8},{"game_id":21400380,"team_id":1610612745,"player_id":203477,"opponent_id":1610612740,"period":"f","season":"2014","min":"10:39","fgm":2,"fga":3,"fg3m":0,"fg3a":1,"ftm":0,"fta":0,"oreb":0,"dreb":0,"ast":1,"blk":0,"stl":"0","to":1,"pf":0,"pts":4,"plus_minus":-9},{"game_id":21400411,"team_id":1610612745,"player_id":203477,"opponent_id":1610612757,"period":"f","season":"2014","min":"3:57","fgm":0,"fga":1,"fg3m":0,"fg3a":1,"ftm":0,"fta":0,"oreb":0,"dreb":0,"ast":0,"blk":0,"stl":"0","to":0,"pf":0,"pts":0,"plus_minus":-6},{"game_id":21400478,"team_id":1610612745,"player_id":203477,"opponent_id":1610612766,"period":"f","season":"2014","min":"2:29","fgm":0,"fga":2,"fg3m":0,"fg3a":2,"ftm":0,"fta":0,"oreb":1,"dreb":1,"ast":0,"blk":0,"stl":"0","to":0,"pf":0,"pts":0,"plus_minus":-1},{"game_id":21400488,"team_id":1610612745,"player_id":203477,"opponent_id":1610612740,"period":"f","season":"2014","min":"12:00","fgm":1,"fga":3,"fg3m":1,"fg3a":3,"ftm":2,"fta":2,"oreb":0,"dreb":1,"ast":2,"blk":0,"stl":"0","to":1,"pf":0,"pts":5,"plus_minus":1},{"game_id":21400497,"team_id":1610612745,"player_id":203477,"opponent_id":1610612748,"period":"f","season":"2014","min":"7:26","fgm":2,"fga":4,"fg3m":2,"fg3a":3,"ftm":2,"fta":3,"oreb":1,"dreb":2,"ast":1,"blk":0,"stl":"0","to":0,"pf":0,"pts":8,"plus_minus":4},{"game_id":21400523,"team_id":1610612745,"player_id":203477,"opponent_id":1610612739,"period":"f","season":"2014","min":"0:16","fgm":0,"fga":0,"fg3m":0,"fg3a":0,"ftm":0,"fta":0,"oreb":0,"dreb":0,"ast":0,"blk":0,"stl":"0","to":0,"pf":0,"pts":0,"plus_minus":0},{"game_id":21400536,"team_id":1610612745,"player_id":203477,"opponent_id":1610612752,"period":"f","season":"2014","min":"6:35","fgm":1,"fga":2,"fg3m":1,"fg3a":2,"ftm":0,"fta":0,"oreb":0,"dreb":1,"ast":1,"blk":0,"stl":"0","to":1,"pf":1,"pts":3,"plus_minus":1},{"game_id":21400555,"team_id":1610612745,"player_id":203477,"opponent_id":1610612762,"period":"f","season":"2014","min":"1:20","fgm":0,"fga":0,"fg3m":0,"fg3a":0,"ftm":0,"fta":0,"oreb":0,"dreb":0,"ast":0,"blk":0,"stl":"0","to":0,"pf":0,"pts":0,"plus_minus":-2},{"game_id":21400709,"team_id":1610612745,"player_id":203477,"opponent_id":1610612765,"period":"f","season":"2014","min":"7:29","fgm":0,"fga":6,"fg3m":0,"fg3a":5,"ftm":0,"fta":0,"oreb":0,"dreb":0,"ast":0,"blk":0,"stl":"0","to":0,"pf":2,"pts":0,"plus_minus":7},{"game_id":21400799,"team_id":1610612745,"player_id":203477,"opponent_id":1610612746,"period":"f","season":"2014","min":"2:10","fgm":0,"fga":1,"fg3m":0,"fg3a":1,"ftm":0,"fta":0,"oreb":0,"dreb":0,"ast":0,"blk":0,"stl":"0","to":0,"pf":0,"pts":0,"plus_minus":-2},{"game_id":21400825,"team_id":1610612755,"player_id":203477,"opponent_id":1610612753,"period":"f","season":"2014","min":"29:21","fgm":5,"fga":12,"fg3m":4,"fg3a":9,"ftm":0,"fta":0,"oreb":2,"dreb":2,"ast":3,"blk":1,"stl":"0","to":3,"pf":5,"pts":14,"plus_minus":-2},{"game_id":21400830,"team_id":1610612755,"player_id":203477,"opponent_id":1610612748,"period":"f","season":"2014","min":"29:37","fgm":4,"fga":9,"fg3m":3,"fg3a":7,"ftm":0,"fta":0,"oreb":1,"dreb":0,"ast":3,"blk":0,"stl":"0","to":3,"pf":3,"pts":11,"plus_minus":-8},{"game_id":21400847,"team_id":1610612755,"player_id":203477,"opponent_id":1610612749,"period":"f","season":"2014","min":"32:37","fgm":3,"fga":10,"fg3m":1,"fg3a":5,"ftm":4,"fta":5,"oreb":1,"dreb":1,"ast":6,"blk":0,"stl":"1","to":5,"pf":4,"pts":11,"plus_minus":-7},{"game_id":21400857,"team_id":1610612755,"player_id":203477,"opponent_id":1610612764,"period":"f","season":"2014","min":"21:33","fgm":3,"fga":11,"fg3m":1,"fg3a":6,"ftm":1,"fta":1,"oreb":1,"dreb":2,"ast":1,"blk":0,"stl":"0","to":1,"pf":2,"pts":8,"plus_minus":-2},{"game_id":21400881,"team_id":1610612755,"player_id":203477,"opponent_id":1610612754,"period":"f","season":"2014","min":"22:24","fgm":2,"fga":8,"fg3m":1,"fg3a":5,"ftm":0,"fta":0,"oreb":0,"dreb":2,"ast":1,"blk":1,"stl":"2","to":0,"pf":3,"pts":5,"plus_minus":-15},{"game_id":21400885,"team_id":1610612755,"player_id":203477,"opponent_id":1610612761,"period":"f","season":"2014","min":"25:12","fgm":5,"fga":12,"fg3m":4,"fg3a":8,"ftm":0,"fta":0,"oreb":0,"dreb":1,"ast":3,"blk":0,"stl":"0","to":0,"pf":2,"pts":14,"plus_minus":-6},{"game_id":21400904,"team_id":1610612755,"player_id":203477,"opponent_id":1610612760,"period":"f","season":"2014","min":"41:36","fgm":10,"fga":16,"fg3m":8,"fg3a":13,"ftm":3,"fta":3,"oreb":0,"dreb":7,"ast":6,"blk":0,"stl":"1","to":3,"pf":1,"pts":31,"plus_minus":5},{"game_id":21400914,"team_id":1610612755,"player_id":203477,"opponent_id":1610612762,"period":"f","season":"2014","min":"28:13","fgm":6,"fga":15,"fg3m":4,"fg3a":9,"ftm":0,"fta":0,"oreb":0,"dreb":2,"ast":4,"blk":0,"stl":"0","to":1,"pf":2,"pts":16,"plus_minus":-3},{"game_id":21400927,"team_id":1610612755,"player_id":203477,"opponent_id":1610612737,"period":"f","season":"2014","min":"36:36","fgm":2,"fga":13,"fg3m":2,"fg3a":9,"ftm":6,"fta":8,"oreb":0,"dreb":5,"ast":8,"blk":0,"stl":"1","to":1,"pf":4,"pts":12,"plus_minus":7},{"game_id":21400953,"team_id":1610612755,"player_id":203477,"opponent_id":1610612741,"period":"f","season":"2014","min":"29:40","fgm":7,"fga":15,"fg3m":4,"fg3a":8,"ftm":2,"fta":2,"oreb":0,"dreb":3,"ast":0,"blk":0,"stl":"0","to":2,"pf":0,"pts":20,"plus_minus":-2},{"game_id":21400968,"team_id":1610612755,"player_id":203477,"opponent_id":1610612758,"period":"f","season":"2014","min":"23:00","fgm":3,"fga":9,"fg3m":1,"fg3a":7,"ftm":0,"fta":0,"oreb":0,"dreb":1,"ast":5,"blk":0,"stl":"0","to":2,"pf":3,"pts":7,"plus_minus":-4},{"game_id":21400978,"team_id":1610612755,"player_id":203477,"opponent_id":1610612751,"period":"f","season":"2014","min":"29:15","fgm":6,"fga":13,"fg3m":1,"fg3a":8,"ftm":0,"fta":0,"oreb":1,"dreb":3,"ast":3,"blk":0,"stl":"0","to":0,"pf":2,"pts":13,"plus_minus":-24},{"game_id":21400992,"team_id":1610612755,"player_id":203477,"opponent_id":1610612738,"period":"f","season":"2014","min":"28:01","fgm":4,"fga":11,"fg3m":2,"fg3a":7,"ftm":1,"fta":2,"oreb":0,"dreb":6,"ast":2,"blk":1,"stl":"0","to":3,"pf":4,"pts":11,"plus_minus":-8},{"game_id":21401006,"team_id":1610612755,"player_id":203477,"opponent_id":1610612765,"period":"f","season":"2014","min":"21:51","fgm":2,"fga":10,"fg3m":2,"fg3a":6,"ftm":3,"fta":4,"oreb":0,"dreb":3,"ast":4,"blk":0,"stl":"1","to":3,"pf":3,"pts":9,"plus_minus":5},{"game_id":21401021,"team_id":1610612755,"player_id":203477,"opponent_id":1610612752,"period":"f","season":"2014","min":"19:35","fgm":4,"fga":11,"fg3m":4,"fg3a":8,"ftm":0,"fta":0,"oreb":0,"dreb":0,"ast":2,"blk":0,"stl":"1","to":1,"pf":0,"pts":12,"plus_minus":17},{"game_id":21401047,"team_id":1610612755,"player_id":203477,"opponent_id":1610612747,"period":"f","season":"2014","min":"21:51","fgm":1,"fga":12,"fg3m":1,"fg3a":6,"ftm":0,"fta":0,"oreb":1,"dreb":0,"ast":2,"blk":0,"stl":"0","to":1,"pf":5,"pts":3,"plus_minus":-1},{"game_id":21401058,"team_id":1610612755,"player_id":203477,"opponent_id":1610612758,"period":"f","season":"2014","min":"19:13","fgm":5,"fga":10,"fg3m":2,"fg3a":6,"ftm":1,"fta":1,"oreb":0,"dreb":0,"ast":1,"blk":0,"stl":"1","to":1,"pf":1,"pts":13,"plus_minus":-5},{"game_id":21401069,"team_id":1610612755,"player_id":203477,"opponent_id":1610612743,"period":"f","season":"2014","min":"22:23","fgm":4,"fga":11,"fg3m":2,"fg3a":5,"ftm":5,"fta":6,"oreb":0,"dreb":3,"ast":1,"blk":0,"stl":"1","to":1,"pf":2,"pts":15,"plus_minus":1},{"game_id":21401075,"team_id":1610612755,"player_id":203477,"opponent_id":1610612746,"period":"f","season":"2014","min":"20:02","fgm":3,"fga":7,"fg3m":3,"fg3a":7,"ftm":0,"fta":0,"oreb":0,"dreb":2,"ast":0,"blk":0,"stl":"0","to":0,"pf":4,"pts":9,"plus_minus":-22},{"game_id":21401092,"team_id":1610612755,"player_id":203477,"opponent_id":1610612739,"period":"f","season":"2014","min":"17:29","fgm":3,"fga":11,"fg3m":2,"fg3a":7,"ftm":0,"fta":0,"oreb":0,"dreb":1,"ast":5,"blk":0,"stl":"1","to":3,"pf":2,"pts":8,"plus_minus":2},{"game_id":21401102,"team_id":1610612755,"player_id":203477,"opponent_id":1610612747,"period":"f","season":"2014","min":"27:20","fgm":4,"fga":9,"fg3m":3,"fg3a":7,"ftm":7,"fta":7,"oreb":0,"dreb":0,"ast":3,"blk":0,"stl":"3","to":3,"pf":1,"pts":18,"plus_minus":-4},{"game_id":21401114,"team_id":1610612755,"player_id":203477,"opponent_id":1610612764,"period":"f","season":"2014","min":"22:07","fgm":7,"fga":12,"fg3m":4,"fg3a":9,"ftm":0,"fta":0,"oreb":0,"dreb":3,"ast":6,"blk":0,"stl":"2","to":2,"pf":2,"pts":18,"plus_minus":4},{"game_id":21500005,"team_id":1610612755,"player_id":203477,"opponent_id":1610612738,"period":"f","season":"2015","min":"37:59","fgm":6,"fga":14,"fg3m":4,"fg3a":10,"ftm":2,"fta":2,"oreb":1,"dreb":6,"ast":2,"blk":0,"stl":"1","to":3,"pf":0,"pts":18,"plus_minus":-3},{"game_id":21500023,"team_id":1610612755,"player_id":203477,"opponent_id":1610612762,"period":"f","season":"2015","min":"31:11","fgm":1,"fga":9,"fg3m":1,"fg3a":6,"ftm":7,"fta":10,"oreb":1,"dreb":4,"ast":2,"blk":0,"stl":"0","to":4,"pf":4,"pts":10,"plus_minus":-16},{"game_id":21500046,"team_id":1610612755,"player_id":203477,"opponent_id":1610612739,"period":"f","season":"2015","min":"30:56","fgm":2,"fga":8,"fg3m":1,"fg3a":3,"ftm":2,"fta":2,"oreb":0,"dreb":2,"ast":1,"blk":0,"stl":"0","to":0,"pf":0,"pts":7,"plus_minus":-19},{"game_id":21500065,"team_id":1610612755,"player_id":203477,"opponent_id":1610612749,"period":"f","season":"2015","min":"15:00","fgm":0,"fga":4,"fg3m":0,"fg3a":3,"ftm":3,"fta":3,"oreb":0,"dreb":1,"ast":1,"blk":1,"stl":"1","to":1,"pf":2,"pts":3,"plus_minus":-16},{"game_id":21500078,"team_id":1610612755,"player_id":203477,"opponent_id":1610612739,"period":"f","season":"2015","min":"21:31","fgm":5,"fga":8,"fg3m":3,"fg3a":5,"ftm":4,"fta":4,"oreb":0,"dreb":0,"ast":4,"blk":0,"stl":"0","to":1,"pf":1,"pts":17,"plus_minus":9},{"game_id":21500087,"team_id":1610612755,"player_id":203477,"opponent_id":1610612753,"period":"f","season":"2015","min":"26:42","fgm":8,"fga":16,"fg3m":6,"fg3a":12,"ftm":1,"fta":1,"oreb":0,"dreb":3,"ast":1,"blk":1,"stl":"3","to":1,"pf":2,"pts":23,"plus_minus":1},{"game_id":21500115,"team_id":1610612755,"player_id":203477,"opponent_id":1610612761,"period":"f","season":"2015","min":"28:43","fgm":5,"fga":11,"fg3m":5,"fg3a":10,"ftm":3,"fta":3,"oreb":0,"dreb":0,"ast":1,"blk":0,"stl":"0","to":2,"pf":2,"pts":18,"plus_minus":-1},{"game_id":21500100,"team_id":1610612755,"player_id":203477,"opponent_id":1610612741,"period":"f","season":"2015","min":"20:50","fgm":1,"fga":5,"fg3m":1,"fg3a":3,"ftm":0,"fta":0,"oreb":0,"dreb":3,"ast":1,"blk":0,"stl":"1","to":0,"pf":0,"pts":3,"plus_minus":-9},{"game_id":21500134,"team_id":1610612755,"player_id":203477,"opponent_id":1610612760,"period":"f","season":"2015","min":"14:52","fgm":0,"fga":4,"fg3m":0,"fg3a":1,"ftm":2,"fta":3,"oreb":0,"dreb":1,"ast":2,"blk":0,"stl":"2","to":0,"pf":1,"pts":2,"plus_minus":2},{"game_id":21500142,"team_id":1610612755,"player_id":203477,"opponent_id":1610612759,"period":"f","season":"2015","min":"26:32","fgm":2,"fga":11,"fg3m":2,"fg3a":6,"ftm":0,"fta":0,"oreb":1,"dreb":4,"ast":3,"blk":0,"stl":"0","to":1,"pf":1,"pts":6,"plus_minus":0},{"game_id":21500152,"team_id":1610612755,"player_id":203477,"opponent_id":1610612742,"period":"f","season":"2015","min":"25:21","fgm":1,"fga":9,"fg3m":1,"fg3a":8,"ftm":0,"fta":1,"oreb":0,"dreb":1,"ast":1,"blk":0,"stl":"1","to":1,"pf":0,"pts":3,"plus_minus":-1},{"game_id":21500167,"team_id":1610612755,"player_id":203477,"opponent_id":1610612754,"period":"f","season":"2015","min":"16:54","fgm":1,"fga":5,"fg3m":1,"fg3a":5,"ftm":0,"fta":0,"oreb":0,"dreb":0,"ast":0,"blk":1,"stl":"0","to":1,"pf":0,"pts":3,"plus_minus":-7},{"game_id":21500178,"team_id":1610612755,"player_id":203477,"opponent_id":1610612766,"period":"f","season":"2015","min":"20:40","fgm":3,"fga":7,"fg3m":1,"fg3a":3,"ftm":1,"fta":2,"oreb":0,"dreb":2,"ast":2,"blk":0,"stl":"1","to":1,"pf":2,"pts":8,"plus_minus":-8},{"game_id":21500193,"team_id":1610612755,"player_id":203477,"opponent_id":1610612748,"period":"f","season":"2015","min":"27:57","fgm":7,"fga":17,"fg3m":5,"fg3a":12,"ftm":3,"fta":3,"oreb":0,"dreb":0,"ast":2,"blk":0,"stl":"1","to":2,"pf":2,"pts":22,"plus_minus":8},{"game_id":21500206,"team_id":1610612755,"player_id":203477,"opponent_id":1610612750,"period":"f","season":"2015","min":"29:32","fgm":3,"fga":10,"fg3m":3,"fg3a":9,"ftm":5,"fta":5,"oreb":1,"dreb":2,"ast":3,"blk":1,"stl":"1","to":3,"pf":5,"pts":14,"plus_minus":-12},{"game_id":21500217,"team_id":1610612755,"player_id":203477,"opponent_id":1610612738,"period":"f","season":"2015","min":"32:22","fgm":3,"fga":9,"fg3m":2,"fg3a":7,"ftm":4,"fta":4,"oreb":0,"dreb":5,"ast":2,"blk":2,"stl":"1","to":2,"pf":2,"pts":12,"plus_minus":-1},{"game_id":21500232,"team_id":1610612755,"player_id":203477,"opponent_id":1610612745,"period":"f","season":"2015","min":"32:23","fgm":9,"fga":17,"fg3m":4,"fg3a":10,"ftm":1,"fta":3,"oreb":0,"dreb":2,"ast":2,"blk":1,"stl":"0","to":3,"pf":5,"pts":23,"plus_minus":-9},{"game_id":21500251,"team_id":1610612755,"player_id":203477,"opponent_id":1610612763,"period":"f","season":"2015","min":"35:21","fgm":5,"fga":15,"fg3m":4,"fg3a":12,"ftm":2,"fta":2,"oreb":0,"dreb":1,"ast":3,"blk":0,"stl":"2","to":4,"pf":3,"pts":16,"plus_minus":-7},{"game_id":21500263,"team_id":1610612755,"player_id":203477,"opponent_id":1610612747,"period":"f","season":"2015","min":"30:19","fgm":4,"fga":9,"fg3m":4,"fg3a":7,"ftm":0,"fta":0,"oreb":0,"dreb":3,"ast":5,"blk":0,"stl":"1","to":0,"pf":1,"pts":12,"plus_minus":13},{"game_id":21500271,"team_id":1610612755,"player_id":203477,"opponent_id":1610612752,"period":"f","season":"2015","min":"30:08","fgm":4,"fga":15,"fg3m":2,"fg3a":6,"ftm":0,"fta":0,"oreb":2,"dreb":3,"ast":3,"blk":0,"stl":"1","to":1,"pf":1,"pts":10,"plus_minus":-6},{"game_id":21500289,"team_id":1610612755,"player_id":203477,"opponent_id":1610612743,"period":"f","season":"2015","min":"24:19","fgm":5,"fga":9,"fg3m":5,"fg3a":8,"ftm":0,"fta":0,"oreb":0,"dreb":1,"ast":1,"blk":0,"stl":"1","to":2,"pf":2,"pts":15,"plus_minus":-7},{"game_id":21500289,"team_id":1610612755,"player_id":203477,"opponent_id":1610612743,"period":"f","season":"2015","min":"24:19","fgm":5,"fga":9,"fg3m":5,"fg3a":8,"ftm":0,"fta":0,"oreb":0,"dreb":1,"ast":1,"blk":0,"stl":"1","to":2,"pf":2,"pts":15,"plus_minus":-7},{"game_id":21500305,"team_id":1610612755,"player_id":203477,"opponent_id":1610612759,"period":"f","season":"2015","min":"27:32","fgm":0,"fga":6,"fg3m":0,"fg3a":5,"ftm":0,"fta":0,"oreb":0,"dreb":1,"ast":5,"blk":0,"stl":"0","to":0,"pf":0,"pts":0,"plus_minus":-22},{"game_id":21500329,"team_id":1610612755,"player_id":203477,"opponent_id":1610612751,"period":"f","season":"2015","min":"25:17","fgm":2,"fga":10,"fg3m":0,"fg3a":6,"ftm":0,"fta":0,"oreb":1,"dreb":2,"ast":3,"blk":1,"stl":"1","to":1,"pf":2,"pts":4,"plus_minus":-9},{"game_id":21500335,"team_id":1610612755,"player_id":203477,"opponent_id":1610612765,"period":"f","season":"2015","min":"22:49","fgm":1,"fga":5,"fg3m":1,"fg3a":3,"ftm":4,"fta":4,"oreb":0,"dreb":1,"ast":2,"blk":0,"stl":"0","to":1,"pf":1,"pts":7,"plus_minus":-1},{"game_id":21500355,"team_id":1610612755,"player_id":203477,"opponent_id":1610612761,"period":"f","season":"2015","min":"36:02","fgm":3,"fga":9,"fg3m":3,"fg3a":8,"ftm":1,"fta":1,"oreb":0,"dreb":1,"ast":3,"blk":0,"stl":"0","to":2,"pf":2,"pts":10,"plus_minus":-9},{"game_id":21500361,"team_id":1610612755,"player_id":203477,"opponent_id":1610612741,"period":"f","season":"2015","min":"29:49","fgm":1,"fga":5,"fg3m":1,"fg3a":3,"ftm":1,"fta":1,"oreb":0,"dreb":1,"ast":3,"blk":0,"stl":"0","to":1,"pf":2,"pts":4,"plus_minus":2},{"game_id":21500376,"team_id":1610612755,"player_id":203477,"opponent_id":1610612737,"period":"f","season":"2015","min":"30:31","fgm":7,"fga":12,"fg3m":6,"fg3a":8,"ftm":4,"fta":5,"oreb":0,"dreb":1,"ast":0,"blk":0,"stl":"1","to":3,"pf":3,"pts":24,"plus_minus":5},{"game_id":21500376,"team_id":1610612755,"player_id":203477,"opponent_id":1610612737,"period":"f","season":"2015","min":"30:31","fgm":7,"fga":12,"fg3m":6,"fg3a":8,"ftm":4,"fta":5,"oreb":0,"dreb":1,"ast":0,"blk":0,"stl":"1","to":3,"pf":3,"pts":24,"plus_minus":5},{"game_id":21500376,"team_id":1610612755,"player_id":203477,"opponent_id":1610612737,"period":"f","season":"2015","min":"30:31","fgm":7,"fga":12,"fg3m":6,"fg3a":8,"ftm":4,"fta":5,"oreb":0,"dreb":1,"ast":0,"blk":0,"stl":"1","to":3,"pf":3,"pts":24,"plus_minus":5},{"game_id":21500376,"team_id":1610612755,"player_id":203477,"opponent_id":1610612737,"period":"f","season":"2015","min":"30:31","fgm":7,"fga":12,"fg3m":6,"fg3a":8,"ftm":4,"fta":5,"oreb":0,"dreb":1,"ast":0,"blk":0,"stl":"1","to":3,"pf":3,"pts":24,"plus_minus":5},{"game_id":21500376,"team_id":1610612755,"player_id":203477,"opponent_id":1610612737,"period":"f","season":"2015","min":"30:31","fgm":7,"fga":12,"fg3m":6,"fg3a":8,"ftm":4,"fta":5,"oreb":0,"dreb":1,"ast":0,"blk":0,"stl":"1","to":3,"pf":3,"pts":24,"plus_minus":5},{"game_id":21500388,"team_id":1610612755,"player_id":203477,"opponent_id":1610612752,"period":"f","season":"2015","min":"28:43","fgm":4,"fga":10,"fg3m":2,"fg3a":6,"ftm":4,"fta":5,"oreb":0,"dreb":0,"ast":3,"blk":0,"stl":"0","to":2,"pf":3,"pts":14,"plus_minus":-20},{"game_id":21500405,"team_id":1610612755,"player_id":203477,"opponent_id":1610612739,"period":"f","season":"2015","min":"21:12","fgm":2,"fga":9,"fg3m":2,"fg3a":6,"ftm":0,"fta":0,"oreb":0,"dreb":2,"ast":0,"blk":0,"stl":"1","to":1,"pf":3,"pts":6,"plus_minus":-26},{"game_id":21500419,"team_id":1610612755,"player_id":203477,"opponent_id":1610612763,"period":"f","season":"2015","min":"30:06","fgm":5,"fga":8,"fg3m":2,"fg3a":5,"ftm":3,"fta":6,"oreb":0,"dreb":1,"ast":1,"blk":1,"stl":"2","to":0,"pf":1,"pts":15,"plus_minus":1},{"game_id":21500430,"team_id":1610612755,"player_id":203477,"opponent_id":1610612749,"period":"f","season":"2015","min":"19:58","fgm":3,"fga":6,"fg3m":2,"fg3a":5,"ftm":2,"fta":3,"oreb":0,"dreb":4,"ast":2,"blk":0,"stl":"1","to":3,"pf":2,"pts":10,"plus_minus":-3},{"game_id":21500451,"team_id":1610612755,"player_id":203477,"opponent_id":1610612756,"period":"f","season":"2015","min":"27:39","fgm":6,"fga":12,"fg3m":4,"fg3a":8,"ftm":6,"fta":6,"oreb":0,"dreb":4,"ast":3,"blk":0,"stl":"1","to":2,"pf":1,"pts":22,"plus_minus":-4},{"game_id":21500467,"team_id":1610612755,"player_id":203477,"opponent_id":1610612762,"period":"f","season":"2015","min":"17:22","fgm":1,"fga":6,"fg3m":0,"fg3a":3,"ftm":2,"fta":4,"oreb":0,"dreb":4,"ast":1,"blk":0,"stl":"0","to":0,"pf":2,"pts":4,"plus_minus":-14},{"game_id":21500483,"team_id":1610612755,"player_id":203477,"opponent_id":1610612758,"period":"f","season":"2015","min":"31:30","fgm":6,"fga":18,"fg3m":3,"fg3a":11,"ftm":0,"fta":0,"oreb":0,"dreb":3,"ast":1,"blk":0,"stl":"1","to":0,"pf":1,"pts":15,"plus_minus":9},{"game_id":21500494,"team_id":1610612755,"player_id":203477,"opponent_id":1610612747,"period":"f","season":"2015","min":"30:58","fgm":2,"fga":11,"fg3m":1,"fg3a":8,"ftm":2,"fta":2,"oreb":0,"dreb":4,"ast":1,"blk":0,"stl":"0","to":3,"pf":1,"pts":7,"plus_minus":-21},{"game_id":21500505,"team_id":1610612755,"player_id":203477,"opponent_id":1610612746,"period":"f","season":"2015","min":"15:03","fgm":0,"fga":5,"fg3m":0,"fg3a":2,"ftm":0,"fta":0,"oreb":2,"dreb":0,"ast":1,"blk":0,"stl":"1","to":0,"pf":3,"pts":0,"plus_minus":-18},{"game_id":21500512,"team_id":1610612755,"player_id":203477,"opponent_id":1610612750,"period":"f","season":"2015","min":"10:21","fgm":2,"fga":6,"fg3m":1,"fg3a":4,"ftm":1,"fta":2,"oreb":0,"dreb":0,"ast":2,"blk":0,"stl":"0","to":0,"pf":1,"pts":6,"plus_minus":6},{"game_id":21500536,"team_id":1610612755,"player_id":203477,"opponent_id":1610612737,"period":"f","season":"2015","min":"16:03","fgm":1,"fga":4,"fg3m":0,"fg3a":3,"ftm":3,"fta":4,"oreb":0,"dreb":1,"ast":1,"blk":0,"stl":"1","to":1,"pf":2,"pts":5,"plus_minus":-33},{"game_id":21500554,"team_id":1610612755,"player_id":203477,"opponent_id":1610612761,"period":"f","season":"2015","min":"9:44","fgm":2,"fga":3,"fg3m":2,"fg3a":2,"ftm":0,"fta":0,"oreb":0,"dreb":0,"ast":1,"blk":0,"stl":"0","to":2,"pf":2,"pts":6,"plus_minus":-11},{"game_id":21500587,"team_id":1610612755,"player_id":203477,"opponent_id":1610612741,"period":"f","season":"2015","min":"4:46","fgm":0,"fga":0,"fg3m":0,"fg3a":0,"ftm":0,"fta":0,"oreb":0,"dreb":0,"ast":0,"blk":0,"stl":"0","to":0,"pf":0,"pts":0,"plus_minus":-2},{"game_id":21500606,"team_id":1610612755,"player_id":203477,"opponent_id":1610612757,"period":"f","season":"2015","min":"31:02","fgm":5,"fga":10,"fg3m":2,"fg3a":5,"ftm":2,"fta":3,"oreb":0,"dreb":4,"ast":4,"blk":1,"stl":"1","to":1,"pf":1,"pts":14,"plus_minus":14},{"game_id":21500615,"team_id":1610612755,"player_id":203477,"opponent_id":1610612752,"period":"f","season":"2015","min":"19:22","fgm":3,"fga":5,"fg3m":3,"fg3a":5,"ftm":5,"fta":6,"oreb":0,"dreb":4,"ast":1,"blk":0,"stl":"0","to":1,"pf":3,"pts":14,"plus_minus":12},{"game_id":21500629,"team_id":1610612755,"player_id":203477,"opponent_id":1610612753,"period":"f","season":"2015","min":"27:51","fgm":5,"fga":8,"fg3m":3,"fg3a":4,"ftm":2,"fta":2,"oreb":0,"dreb":1,"ast":1,"blk":0,"stl":"2","to":2,"pf":1,"pts":15,"plus_minus":14},{"game_id":21500656,"team_id":1610612755,"player_id":203477,"opponent_id":1610612738,"period":"f","season":"2015","min":"15:20","fgm":2,"fga":4,"fg3m":1,"fg3a":3,"ftm":2,"fta":2,"oreb":0,"dreb":3,"ast":1,"blk":0,"stl":"1","to":5,"pf":2,"pts":7,"plus_minus":-7},{"game_id":21500677,"team_id":1610612755,"player_id":203477,"opponent_id":1610612756,"period":"f","season":"2015","min":"9:53","fgm":3,"fga":6,"fg3m":1,"fg3a":3,"ftm":0,"fta":0,"oreb":0,"dreb":0,"ast":0,"blk":0,"stl":"1","to":0,"pf":0,"pts":7,"plus_minus":2},{"game_id":21500686,"team_id":1610612755,"player_id":203477,"opponent_id":1610612765,"period":"f","season":"2015","min":"22:46","fgm":2,"fga":8,"fg3m":2,"fg3a":5,"ftm":1,"fta":1,"oreb":0,"dreb":2,"ast":3,"blk":0,"stl":"0","to":0,"pf":1,"pts":7,"plus_minus":-4},{"game_id":21500707,"team_id":1610612755,"player_id":203477,"opponent_id":1610612744,"period":"f","season":"2015","min":"30:03","fgm":5,"fga":11,"fg3m":5,"fg3a":9,"ftm":3,"fta":3,"oreb":1,"dreb":3,"ast":2,"blk":0,"stl":"4","to":0,"pf":0,"pts":18,"plus_minus":16},{"game_id":21500736,"team_id":1610612755,"player_id":203477,"opponent_id":1610612737,"period":"f","season":"2015","min":"19:58","fgm":4,"fga":10,"fg3m":3,"fg3a":6,"ftm":0,"fta":0,"oreb":0,"dreb":2,"ast":1,"blk":0,"stl":"0","to":1,"pf":2,"pts":11,"plus_minus":-27},{"game_id":21500753,"team_id":1610612755,"player_id":203477,"opponent_id":1610612764,"period":"f","season":"2015","min":"31:50","fgm":5,"fga":12,"fg3m":4,"fg3a":8,"ftm":4,"fta":4,"oreb":0,"dreb":3,"ast":3,"blk":0,"stl":"1","to":3,"pf":1,"pts":18,"plus_minus":15},{"game_id":21500764,"team_id":1610612755,"player_id":203477,"opponent_id":1610612751,"period":"f","season":"2015","min":"24:15","fgm":2,"fga":9,"fg3m":2,"fg3a":6,"ftm":0,"fta":0,"oreb":1,"dreb":2,"ast":3,"blk":0,"stl":"1","to":0,"pf":2,"pts":6,"plus_minus":7},{"game_id":21500777,"team_id":1610612755,"player_id":203477,"opponent_id":1610612746,"period":"f","season":"2015","min":"24:50","fgm":0,"fga":6,"fg3m":0,"fg3a":5,"ftm":1,"fta":2,"oreb":0,"dreb":4,"ast":2,"blk":0,"stl":"0","to":2,"pf":5,"pts":1,"plus_minus":-11},{"game_id":21500791,"team_id":1610612755,"player_id":203477,"opponent_id":1610612758,"period":"f","season":"2015","min":"16:19","fgm":2,"fga":7,"fg3m":2,"fg3a":5,"ftm":0,"fta":0,"oreb":0,"dreb":0,"ast":0,"blk":0,"stl":"0","to":0,"pf":4,"pts":6,"plus_minus":-5},{"game_id":21500811,"team_id":1610612755,"player_id":203477,"opponent_id":1610612740,"period":"f","season":"2015","min":"22:22","fgm":4,"fga":10,"fg3m":4,"fg3a":7,"ftm":1,"fta":1,"oreb":1,"dreb":2,"ast":0,"blk":0,"stl":"1","to":1,"pf":0,"pts":13,"plus_minus":-5},{"game_id":21500830,"team_id":1610612755,"player_id":203477,"opponent_id":1610612742,"period":"f","season":"2015","min":"26:48","fgm":6,"fga":12,"fg3m":3,"fg3a":8,"ftm":0,"fta":0,"oreb":0,"dreb":1,"ast":1,"blk":0,"stl":"0","to":2,"pf":4,"pts":15,"plus_minus":-17},{"game_id":21500840,"team_id":1610612755,"player_id":203477,"opponent_id":1610612753,"period":"f","season":"2015","min":"19:59","fgm":4,"fga":7,"fg3m":2,"fg3a":3,"ftm":2,"fta":2,"oreb":0,"dreb":4,"ast":0,"blk":0,"stl":"1","to":1,"pf":0,"pts":12,"plus_minus":-2},{"game_id":21500847,"team_id":1610612755,"player_id":203477,"opponent_id":1610612765,"period":"f","season":"2015","min":"18:13","fgm":2,"fga":8,"fg3m":0,"fg3a":3,"ftm":2,"fta":4,"oreb":0,"dreb":2,"ast":0,"blk":0,"stl":"1","to":0,"pf":1,"pts":6,"plus_minus":-11},{"game_id":21500862,"team_id":1610612755,"player_id":203477,"opponent_id":1610612764,"period":"f","season":"2015","min":"16:48","fgm":1,"fga":7,"fg3m":1,"fg3a":4,"ftm":4,"fta":4,"oreb":1,"dreb":0,"ast":0,"blk":0,"stl":"0","to":0,"pf":2,"pts":7,"plus_minus":-15},{"game_id":21500881,"team_id":1610612755,"player_id":203477,"opponent_id":1610612753,"period":"f","season":"2015","min":"33:45","fgm":6,"fga":13,"fg3m":3,"fg3a":9,"ftm":3,"fta":3,"oreb":0,"dreb":3,"ast":2,"blk":0,"stl":"0","to":1,"pf":3,"pts":18,"plus_minus":1},{"game_id":21500885,"team_id":1610612755,"player_id":203477,"opponent_id":1610612764,"period":"f","season":"2015","min":"31:56","fgm":5,"fga":12,"fg3m":3,"fg3a":8,"ftm":0,"fta":1,"oreb":0,"dreb":3,"ast":3,"blk":0,"stl":"0","to":0,"pf":1,"pts":13,"plus_minus":2},{"game_id":21500898,"team_id":1610612755,"player_id":203477,"opponent_id":1610612766,"period":"f","season":"2015","min":"32:12","fgm":5,"fga":15,"fg3m":4,"fg3a":10,"ftm":3,"fta":3,"oreb":0,"dreb":0,"ast":0,"blk":0,"stl":"2","to":2,"pf":2,"pts":17,"plus_minus":-4},{"game_id":21500914,"team_id":1610612755,"player_id":203477,"opponent_id":1610612748,"period":"f","season":"2015","min":"28:04","fgm":1,"fga":9,"fg3m":0,"fg3a":5,"ftm":2,"fta":2,"oreb":0,"dreb":3,"ast":3,"blk":0,"stl":"2","to":0,"pf":1,"pts":4,"plus_minus":-9},{"game_id":21500935,"team_id":1610612755,"player_id":203477,"opponent_id":1610612748,"period":"f","season":"2015","min":"32:55","fgm":6,"fga":15,"fg3m":4,"fg3a":12,"ftm":1,"fta":1,"oreb":1,"dreb":2,"ast":4,"blk":0,"stl":"0","to":0,"pf":5,"pts":17,"plus_minus":7},{"game_id":21500951,"team_id":1610612755,"player_id":203477,"opponent_id":1610612745,"period":"f","season":"2015","min":"23:48","fgm":4,"fga":13,"fg3m":4,"fg3a":9,"ftm":2,"fta":2,"oreb":0,"dreb":1,"ast":4,"blk":0,"stl":"0","to":1,"pf":3,"pts":14,"plus_minus":-18},{"game_id":21500964,"team_id":1610612755,"player_id":203477,"opponent_id":1610612751,"period":"f","season":"2015","min":"27:03","fgm":2,"fga":7,"fg3m":0,"fg3a":5,"ftm":0,"fta":0,"oreb":0,"dreb":3,"ast":1,"blk":0,"stl":"0","to":0,"pf":3,"pts":4,"plus_minus":-16},{"game_id":21500976,"team_id":1610612755,"player_id":203477,"opponent_id":1610612765,"period":"f","season":"2015","min":"32:36","fgm":5,"fga":8,"fg3m":4,"fg3a":5,"ftm":8,"fta":9,"oreb":0,"dreb":1,"ast":1,"blk":0,"stl":"2","to":3,"pf":2,"pts":22,"plus_minus":-21},{"game_id":21500999,"team_id":1610612755,"player_id":203477,"opponent_id":1610612751,"period":"f","season":"2015","min":"31:48","fgm":5,"fga":10,"fg3m":5,"fg3a":10,"ftm":5,"fta":5,"oreb":1,"dreb":1,"ast":1,"blk":0,"stl":"0","to":1,"pf":2,"pts":20,"plus_minus":-5},{"game_id":21501013,"team_id":1610612755,"player_id":203477,"opponent_id":1610612764,"period":"f","season":"2015","min":"33:49","fgm":4,"fga":10,"fg3m":1,"fg3a":6,"ftm":6,"fta":7,"oreb":1,"dreb":3,"ast":4,"blk":0,"stl":"1","to":2,"pf":2,"pts":15,"plus_minus":10},{"game_id":21501021,"team_id":1610612755,"player_id":203477,"opponent_id":1610612760,"period":"f","season":"2015","min":"30:41","fgm":3,"fga":9,"fg3m":3,"fg3a":7,"ftm":1,"fta":2,"oreb":0,"dreb":4,"ast":2,"blk":0,"stl":"3","to":0,"pf":1,"pts":10,"plus_minus":-21},{"game_id":21501039,"team_id":1610612755,"player_id":203477,"opponent_id":1610612738,"period":"f","season":"2015","min":"27:15","fgm":3,"fga":10,"fg3m":1,"fg3a":6,"ftm":1,"fta":1,"oreb":1,"dreb":2,"ast":4,"blk":0,"stl":"1","to":1,"pf":0,"pts":8,"plus_minus":-10},{"game_id":21501045,"team_id":1610612755,"player_id":203477,"opponent_id":1610612754,"period":"f","season":"2015","min":"29:56","fgm":6,"fga":14,"fg3m":3,"fg3a":7,"ftm":0,"fta":0,"oreb":2,"dreb":2,"ast":0,"blk":0,"stl":"0","to":2,"pf":0,"pts":15,"plus_minus":-8},{"game_id":21501064,"team_id":1610612755,"player_id":203477,"opponent_id":1610612743,"period":"f","season":"2015","min":"27:25","fgm":4,"fga":11,"fg3m":3,"fg3a":10,"ftm":0,"fta":0,"oreb":0,"dreb":2,"ast":3,"blk":0,"stl":"0","to":1,"pf":1,"pts":11,"plus_minus":-15},{"game_id":21501091,"team_id":1610612755,"player_id":203477,"opponent_id":1610612757,"period":"f","season":"2015","min":"23:54","fgm":2,"fga":11,"fg3m":0,"fg3a":5,"ftm":2,"fta":2,"oreb":0,"dreb":2,"ast":0,"blk":0,"stl":"0","to":0,"pf":1,"pts":6,"plus_minus":-19},{"game_id":21501094,"team_id":1610612755,"player_id":203477,"opponent_id":1610612744,"period":"f","season":"2015","min":"28:13","fgm":3,"fga":9,"fg3m":3,"fg3a":6,"ftm":6,"fta":6,"oreb":0,"dreb":0,"ast":2,"blk":0,"stl":"0","to":1,"pf":3,"pts":15,"plus_minus":-15},{"game_id":21501109,"team_id":1610612755,"player_id":203477,"opponent_id":1610612766,"period":"f","season":"2015","min":"27:14","fgm":3,"fga":10,"fg3m":3,"fg3a":8,"ftm":1,"fta":1,"oreb":0,"dreb":3,"ast":1,"blk":0,"stl":"1","to":1,"pf":3,"pts":10,"plus_minus":-21},{"game_id":21501128,"team_id":1610612755,"player_id":203477,"opponent_id":1610612766,"period":"f","season":"2015","min":"24:09","fgm":1,"fga":9,"fg3m":0,"fg3a":6,"ftm":2,"fta":3,"oreb":0,"dreb":2,"ast":1,"blk":2,"stl":"1","to":0,"pf":1,"pts":4,"plus_minus":-20},{"game_id":21501138,"team_id":1610612755,"player_id":203477,"opponent_id":1610612754,"period":"f","season":"2015","min":"39:14","fgm":7,"fga":15,"fg3m":5,"fg3a":12,"ftm":5,"fta":7,"oreb":0,"dreb":4,"ast":2,"blk":0,"stl":"0","to":1,"pf":1,"pts":24,"plus_minus":-5},{"game_id":21501154,"team_id":1610612755,"player_id":203477,"opponent_id":1610612740,"period":"f","season":"2015","min":"22:46","fgm":6,"fga":12,"fg3m":4,"fg3a":7,"ftm":0,"fta":0,"oreb":0,"dreb":2,"ast":2,"blk":0,"stl":"1","to":0,"pf":1,"pts":16,"plus_minus":-10},{"game_id":21300421,"team_id":1610612745,"player_id":203477,"opponent_id":1610612759,"period":"f","season":"2013","min":"0:23","fgm":0,"fga":0,"fg3m":0,"fg3a":0,"ftm":0,"fta":0,"oreb":0,"dreb":0,"ast":0,"blk":0,"stl":"0","to":0,"pf":0,"pts":0,"plus_minus":0},{"game_id":21300450,"team_id":1610612745,"player_id":203477,"opponent_id":1610612760,"period":"f","season":"2013","min":"7:29","fgm":1,"fga":3,"fg3m":0,"fg3a":2,"ftm":2,"fta":2,"oreb":0,"dreb":0,"ast":0,"blk":0,"stl":"0","to":0,"pf":0,"pts":4,"plus_minus":-7},{"game_id":21300526,"team_id":1610612745,"player_id":203477,"opponent_id":1610612747,"period":"f","season":"2013","min":"1:32","fgm":0,"fga":0,"fg3m":0,"fg3a":0,"ftm":0,"fta":0,"oreb":0,"dreb":0,"ast":0,"blk":0,"stl":"0","to":0,"pf":0,"pts":0,"plus_minus":-3},{"game_id":21300572,"team_id":1610612745,"player_id":203477,"opponent_id":1610612740,"period":"f","season":"2013","min":"9:19","fgm":0,"fga":1,"fg3m":0,"fg3a":1,"ftm":0,"fta":0,"oreb":0,"dreb":0,"ast":0,"blk":0,"stl":"0","to":0,"pf":3,"pts":0,"plus_minus":-8},{"game_id":21300597,"team_id":1610612745,"player_id":203477,"opponent_id":1610612749,"period":"f","season":"2013","min":"0:54","fgm":0,"fga":0,"fg3m":0,"fg3a":0,"ftm":2,"fta":2,"oreb":0,"dreb":1,"ast":0,"blk":0,"stl":"0","to":0,"pf":0,"pts":2,"plus_minus":-2},{"game_id":21300852,"team_id":1610612745,"player_id":203477,"opponent_id":1610612758,"period":"f","season":"2013","min":"7:35","fgm":1,"fga":3,"fg3m":0,"fg3a":1,"ftm":1,"fta":1,"oreb":1,"dreb":0,"ast":0,"blk":0,"stl":"0","to":1,"pf":0,"pts":3,"plus_minus":1},{"game_id":21300905,"team_id":1610612745,"player_id":203477,"opponent_id":1610612753,"period":"f","season":"2013","min":"1:32","fgm":0,"fga":0,"fg3m":0,"fg3a":0,"ftm":0,"fta":0,"oreb":0,"dreb":0,"ast":1,"blk":0,"stl":"0","to":0,"pf":0,"pts":0,"plus_minus":-2},{"game_id":21300926,"team_id":1610612745,"player_id":203477,"opponent_id":1610612754,"period":"f","season":"2013","min":"5:32","fgm":1,"fga":1,"fg3m":1,"fg3a":1,"ftm":2,"fta":2,"oreb":0,"dreb":0,"ast":0,"blk":0,"stl":"1","to":1,"pf":1,"pts":5,"plus_minus":-2},{"game_id":21300968,"team_id":1610612745,"player_id":203477,"opponent_id":1610612741,"period":"f","season":"2013","min":"8:12","fgm":1,"fga":5,"fg3m":0,"fg3a":2,"ftm":2,"fta":2,"oreb":2,"dreb":0,"ast":1,"blk":0,"stl":"0","to":0,"pf":1,"pts":4,"plus_minus":0},{"game_id":21301000,"team_id":1610612745,"player_id":203477,"opponent_id":1610612762,"period":"f","season":"2013","min":"8:19","fgm":1,"fga":4,"fg3m":1,"fg3a":2,"ftm":0,"fta":0,"oreb":0,"dreb":1,"ast":2,"blk":0,"stl":"2","to":1,"pf":0,"pts":3,"plus_minus":15},{"game_id":21301019,"team_id":1610612745,"player_id":203477,"opponent_id":1610612750,"period":"f","season":"2013","min":"3:11","fgm":2,"fga":3,"fg3m":1,"fg3a":2,"ftm":0,"fta":0,"oreb":0,"dreb":0,"ast":0,"blk":0,"stl":"0","to":0,"pf":1,"pts":5,"plus_minus":3},{"game_id":21301033,"team_id":1610612745,"player_id":203477,"opponent_id":1610612739,"period":"f","season":"2013","min":"5:20","fgm":0,"fga":1,"fg3m":0,"fg3a":1,"ftm":3,"fta":4,"oreb":0,"dreb":0,"ast":0,"blk":0,"stl":"0","to":1,"pf":1,"pts":3,"plus_minus":-12},{"game_id":21301072,"team_id":1610612745,"player_id":203477,"opponent_id":1610612755,"period":"f","season":"2013","min":"13:49","fgm":2,"fga":6,"fg3m":1,"fg3a":3,"ftm":0,"fta":0,"oreb":0,"dreb":1,"ast":0,"blk":1,"stl":"1","to":3,"pf":2,"pts":5,"plus_minus":3},{"game_id":21301088,"team_id":1610612745,"player_id":203477,"opponent_id":1610612746,"period":"f","season":"2013","min":"20:29","fgm":3,"fga":5,"fg3m":2,"fg3a":4,"ftm":6,"fta":8,"oreb":0,"dreb":4,"ast":3,"blk":0,"stl":"0","to":4,"pf":2,"pts":14,"plus_minus":-7},{"game_id":21301111,"team_id":1610612745,"player_id":203477,"opponent_id":1610612751,"period":"f","season":"2013","min":"23:10","fgm":1,"fga":8,"fg3m":0,"fg3a":4,"ftm":0,"fta":0,"oreb":0,"dreb":1,"ast":0,"blk":0,"stl":"0","to":2,"pf":1,"pts":2,"plus_minus":-1},{"game_id":21301118,"team_id":1610612745,"player_id":203477,"opponent_id":1610612761,"period":"f","season":"2013","min":"17:38","fgm":2,"fga":8,"fg3m":2,"fg3a":5,"ftm":1,"fta":2,"oreb":1,"dreb":3,"ast":1,"blk":0,"stl":"1","to":0,"pf":2,"pts":7,"plus_minus":-2},{"game_id":21301139,"team_id":1610612745,"player_id":203477,"opponent_id":1610612760,"period":"f","season":"2013","min":"18:00","fgm":2,"fga":5,"fg3m":2,"fg3a":3,"ftm":0,"fta":0,"oreb":0,"dreb":2,"ast":1,"blk":0,"stl":"0","to":2,"pf":2,"pts":6,"plus_minus":2},{"game_id":21301153,"team_id":1610612745,"player_id":203477,"opponent_id":1610612743,"period":"f","season":"2013","min":"18:36","fgm":5,"fga":8,"fg3m":4,"fg3a":7,"ftm":1,"fta":2,"oreb":1,"dreb":0,"ast":2,"blk":1,"stl":"0","to":0,"pf":2,"pts":15,"plus_minus":-4},{"game_id":21301161,"team_id":1610612745,"player_id":203477,"opponent_id":1610612747,"period":"f","season":"2013","min":"26:52","fgm":6,"fga":8,"fg3m":3,"fg3a":4,"ftm":0,"fta":0,"oreb":0,"dreb":1,"ast":1,"blk":0,"stl":"0","to":2,"pf":1,"pts":15,"plus_minus":0},{"game_id":21301171,"team_id":1610612745,"player_id":203477,"opponent_id":1610612743,"period":"f","season":"2013","min":"24:09","fgm":2,"fga":10,"fg3m":1,"fg3a":8,"ftm":1,"fta":2,"oreb":2,"dreb":1,"ast":6,"blk":2,"stl":"2","to":4,"pf":3,"pts":6,"plus_minus":3},{"game_id":21301183,"team_id":1610612745,"player_id":203477,"opponent_id":1610612750,"period":"f","season":"2013","min":"4:22","fgm":0,"fga":2,"fg3m":0,"fg3a":2,"ftm":0,"fta":0,"oreb":0,"dreb":1,"ast":0,"blk":0,"stl":"0","to":0,"pf":1,"pts":0,"plus_minus":-8},{"game_id":21301219,"team_id":1610612745,"player_id":203477,"opponent_id":1610612740,"period":"f","season":"2013","min":"25:51","fgm":1,"fga":6,"fg3m":0,"fg3a":3,"ftm":0,"fta":2,"oreb":0,"dreb":1,"ast":4,"blk":0,"stl":"1","to":0,"pf":2,"pts":2,"plus_minus":-8},{"game_id":21600015,"team_id":1610612741,"player_id":203477,"opponent_id":1610612738,"period":"f","season":"2016","min":"6:47","fgm":0,"fga":3,"fg3m":0,"fg3a":3,"ftm":0,"fta":0,"oreb":0,"dreb":2,"ast":1,"blk":0,"stl":"1","to":0,"pf":0,"pts":0,"plus_minus":-2},{"game_id":21600030,"team_id":1610612741,"player_id":203477,"opponent_id":1610612754,"period":"f","season":"2016","min":"14:11","fgm":4,"fga":6,"fg3m":3,"fg3a":5,"ftm":0,"fta":0,"oreb":0,"dreb":0,"ast":2,"blk":0,"stl":"1","to":0,"pf":1,"pts":11,"plus_minus":3},{"game_id":21600043,"team_id":1610612741,"player_id":203477,"opponent_id":1610612751,"period":"f","season":"2016","min":"22:01","fgm":5,"fga":7,"fg3m":3,"fg3a":4,"ftm":2,"fta":2,"oreb":1,"dreb":2,"ast":6,"blk":0,"stl":"1","to":0,"pf":2,"pts":15,"plus_minus":8},{"game_id":21600061,"team_id":1610612741,"player_id":203477,"opponent_id":1610612738,"period":"f","season":"2016","min":"19:13","fgm":1,"fga":4,"fg3m":1,"fg3a":3,"ftm":1,"fta":2,"oreb":0,"dreb":0,"ast":3,"blk":0,"stl":"1","to":1,"pf":2,"pts":4,"plus_minus":-1},{"game_id":21600073,"team_id":1610612741,"player_id":203477,"opponent_id":1610612752,"period":"f","season":"2016","min":"14:16","fgm":2,"fga":5,"fg3m":0,"fg3a":2,"ftm":0,"fta":0,"oreb":0,"dreb":1,"ast":1,"blk":0,"stl":"0","to":0,"pf":0,"pts":4,"plus_minus":3},{"game_id":21600083,"team_id":1610612741,"player_id":203477,"opponent_id":1610612754,"period":"f","season":"2016","min":"13:51","fgm":0,"fga":1,"fg3m":0,"fg3a":1,"ftm":2,"fta":2,"oreb":0,"dreb":0,"ast":1,"blk":0,"stl":"2","to":1,"pf":0,"pts":2,"plus_minus":-20},{"game_id":21600096,"team_id":1610612741,"player_id":203477,"opponent_id":1610612753,"period":"f","season":"2016","min":"20:49","fgm":3,"fga":6,"fg3m":1,"fg3a":3,"ftm":3,"fta":4,"oreb":0,"dreb":4,"ast":0,"blk":0,"stl":"0","to":0,"pf":1,"pts":10,"plus_minus":17},{"game_id":21600111,"team_id":1610612741,"player_id":203477,"opponent_id":1610612737,"period":"f","season":"2016","min":"21:42","fgm":3,"fga":9,"fg3m":2,"fg3a":5,"ftm":0,"fta":0,"oreb":0,"dreb":3,"ast":2,"blk":1,"stl":"0","to":1,"pf":2,"pts":8,"plus_minus":-15},{"game_id":21600118,"team_id":1610612741,"player_id":203477,"opponent_id":1610612748,"period":"f","season":"2016","min":"9:04","fgm":0,"fga":1,"fg3m":0,"fg3a":1,"ftm":0,"fta":0,"oreb":0,"dreb":1,"ast":0,"blk":0,"stl":"0","to":0,"pf":0,"pts":0,"plus_minus":-8},{"game_id":21600133,"team_id":1610612741,"player_id":203477,"opponent_id":1610612764,"period":"f","season":"2016","min":"26:51","fgm":3,"fga":7,"fg3m":1,"fg3a":5,"ftm":1,"fta":1,"oreb":0,"dreb":2,"ast":0,"blk":0,"stl":"0","to":0,"pf":2,"pts":8,"plus_minus":6},{"game_id":21600156,"team_id":1610612741,"player_id":203477,"opponent_id":1610612757,"period":"f","season":"2016","min":"24:06","fgm":2,"fga":6,"fg3m":1,"fg3a":4,"ftm":3,"fta":3,"oreb":0,"dreb":1,"ast":0,"blk":0,"stl":"0","to":0,"pf":3,"pts":8,"plus_minus":8},{"game_id":21600173,"team_id":1610612741,"player_id":203477,"opponent_id":1610612762,"period":"f","season":"2016","min":"25:47","fgm":4,"fga":9,"fg3m":0,"fg3a":1,"ftm":0,"fta":0,"oreb":0,"dreb":2,"ast":0,"blk":0,"stl":"1","to":2,"pf":2,"pts":8,"plus_minus":7},{"game_id":21600192,"team_id":1610612741,"player_id":203477,"opponent_id":1610612746,"period":"f","season":"2016","min":"17:19","fgm":2,"fga":5,"fg3m":1,"fg3a":4,"ftm":3,"fta":4,"oreb":0,"dreb":0,"ast":2,"blk":0,"stl":"0","to":0,"pf":4,"pts":8,"plus_minus":0},{"game_id":21600198,"team_id":1610612741,"player_id":203477,"opponent_id":1610612747,"period":"f","season":"2016","min":"30:40","fgm":6,"fga":10,"fg3m":3,"fg3a":6,"ftm":2,"fta":2,"oreb":0,"dreb":2,"ast":0,"blk":0,"stl":"2","to":3,"pf":0,"pts":17,"plus_minus":10},{"game_id":21600210,"team_id":1610612741,"player_id":203477,"opponent_id":1610612743,"period":"f","season":"2016","min":"17:58","fgm":1,"fga":6,"fg3m":0,"fg3a":4,"ftm":0,"fta":0,"oreb":0,"dreb":1,"ast":0,"blk":0,"stl":"2","to":0,"pf":1,"pts":2,"plus_minus":-22},{"game_id":21600229,"team_id":1610612741,"player_id":203477,"opponent_id":1610612755,"period":"f","season":"2016","min":"25:47","fgm":2,"fga":9,"fg3m":2,"fg3a":7,"ftm":2,"fta":2,"oreb":0,"dreb":5,"ast":1,"blk":0,"stl":"1","to":2,"pf":1,"pts":8,"plus_minus":12},{"game_id":21600269,"team_id":1610612741,"player_id":203477,"opponent_id":1610612747,"period":"f","season":"2016","min":"25:44","fgm":2,"fga":9,"fg3m":1,"fg3a":5,"ftm":0,"fta":0,"oreb":1,"dreb":0,"ast":1,"blk":0,"stl":"1","to":1,"pf":0,"pts":5,"plus_minus":-19},{"game_id":21600286,"team_id":1610612741,"player_id":203477,"opponent_id":1610612739,"period":"f","season":"2016","min":"27:48","fgm":4,"fga":8,"fg3m":1,"fg3a":5,"ftm":0,"fta":0,"oreb":0,"dreb":0,"ast":0,"blk":0,"stl":"0","to":0,"pf":2,"pts":9,"plus_minus":-1},{"game_id":21600296,"team_id":1610612741,"player_id":203477,"opponent_id":1610612742,"period":"f","season":"2016","min":"28:35","fgm":4,"fga":6,"fg3m":1,"fg3a":2,"ftm":1,"fta":1,"oreb":0,"dreb":3,"ast":1,"blk":0,"stl":"1","to":2,"pf":1,"pts":10,"plus_minus":-5},{"game_id":21600308,"team_id":1610612741,"player_id":203477,"opponent_id":1610612757,"period":"f","season":"2016","min":"28:46","fgm":4,"fga":11,"fg3m":0,"fg3a":3,"ftm":2,"fta":2,"oreb":3,"dreb":1,"ast":1,"blk":0,"stl":"2","to":2,"pf":3,"pts":10,"plus_minus":-9},{"game_id":21600317,"team_id":1610612741,"player_id":203477,"opponent_id":1610612765,"period":"f","season":"2016","min":"23:04","fgm":1,"fga":5,"fg3m":0,"fg3a":2,"ftm":0,"fta":0,"oreb":0,"dreb":3,"ast":1,"blk":0,"stl":"1","to":0,"pf":3,"pts":2,"plus_minus":-12},{"game_id":21600336,"team_id":1610612741,"player_id":203477,"opponent_id":1610612759,"period":"f","season":"2016","min":"10:16","fgm":0,"fga":2,"fg3m":0,"fg3a":1,"ftm":0,"fta":0,"oreb":0,"dreb":0,"ast":0,"blk":0,"stl":"0","to":1,"pf":1,"pts":0,"plus_minus":-3},{"game_id":21600370,"team_id":1610612741,"player_id":203477,"opponent_id":1610612750,"period":"f","season":"2016","min":"26:42","fgm":3,"fga":9,"fg3m":0,"fg3a":3,"ftm":0,"fta":0,"oreb":0,"dreb":3,"ast":3,"blk":0,"stl":"1","to":1,"pf":1,"pts":6,"plus_minus":-12},{"game_id":21600393,"team_id":1610612741,"player_id":203477,"opponent_id":1610612749,"period":"f","season":"2016","min":"12:00","fgm":0,"fga":4,"fg3m":0,"fg3a":2,"ftm":0,"fta":0,"oreb":0,"dreb":0,"ast":1,"blk":0,"stl":"0","to":0,"pf":1,"pts":0,"plus_minus":-4},{"game_id":21600414,"team_id":1610612741,"player_id":203477,"opponent_id":1610612765,"period":"f","season":"2016","min":"4:35","fgm":0,"fga":1,"fg3m":0,"fg3a":1,"ftm":0,"fta":0,"oreb":0,"dreb":1,"ast":0,"blk":0,"stl":"1","to":0,"pf":0,"pts":0,"plus_minus":-2},{"game_id":21600503,"team_id":1610612741,"player_id":203477,"opponent_id":1610612749,"period":"f","season":"2016","min":"2:16","fgm":0,"fga":0,"fg3m":0,"fg3a":0,"ftm":0,"fta":0,"oreb":0,"dreb":0,"ast":0,"blk":0,"stl":"0","to":0,"pf":0,"pts":0,"plus_minus":-5},{"game_id":21600569,"team_id":1610612741,"player_id":203477,"opponent_id":1610612760,"period":"f","season":"2016","min":"8:26","fgm":1,"fga":3,"fg3m":1,"fg3a":1,"ftm":2,"fta":2,"oreb":1,"dreb":0,"ast":2,"blk":0,"stl":"0","to":1,"pf":0,"pts":5,"plus_minus":5},{"game_id":21600571,"team_id":1610612741,"player_id":203477,"opponent_id":1610612764,"period":"f","season":"2016","min":"10:15","fgm":0,"fga":0,"fg3m":0,"fg3a":0,"ftm":0,"fta":0,"oreb":0,"dreb":1,"ast":0,"blk":0,"stl":"0","to":1,"pf":0,"pts":0,"plus_minus":-9},{"game_id":21600740,"team_id":1610612741,"player_id":203477,"opponent_id":1610612760,"period":"f","season":"2016","min":"6:53","fgm":1,"fga":2,"fg3m":1,"fg3a":1,"ftm":0,"fta":0,"oreb":0,"dreb":1,"ast":1,"blk":0,"stl":"0","to":0,"pf":0,"pts":3,"plus_minus":2},{"game_id":21600792,"team_id":1610612741,"player_id":203477,"opponent_id":1610612744,"period":"f","season":"2016","min":"22:48","fgm":2,"fga":4,"fg3m":0,"fg3a":1,"ftm":2,"fta":2,"oreb":0,"dreb":2,"ast":2,"blk":0,"stl":"0","to":0,"pf":1,"pts":6,"plus_minus":-15},{"game_id":21600807,"team_id":1610612741,"player_id":203477,"opponent_id":1610612756,"period":"f","season":"2016","min":"4:20","fgm":0,"fga":0,"fg3m":0,"fg3a":0,"ftm":0,"fta":0,"oreb":0,"dreb":0,"ast":1,"blk":0,"stl":"0","to":0,"pf":0,"pts":0,"plus_minus":-1},{"game_id":21600816,"team_id":1610612741,"player_id":203477,"opponent_id":1610612750,"period":"f","season":"2016","min":"18:39","fgm":1,"fga":6,"fg3m":1,"fg3a":3,"ftm":2,"fta":2,"oreb":0,"dreb":0,"ast":1,"blk":0,"stl":"2","to":0,"pf":1,"pts":5,"plus_minus":-6},{"game_id":21600831,"team_id":1610612741,"player_id":203477,"opponent_id":1610612761,"period":"f","season":"2016","min":"0:25","fgm":0,"fga":0,"fg3m":0,"fg3a":0,"ftm":0,"fta":0,"oreb":0,"dreb":0,"ast":0,"blk":0,"stl":"0","to":0,"pf":0,"pts":0,"plus_minus":0}]