[{"game_id":21200686,"team_id":1610612738,"player_id":203097,"opponent_id":1610612753,"period":"f","season":"2012","min":"2:38","off_rating":"100.0","def_rating":"120.0","ast_pct":"0.000","ast_tov":"0.000","ast_ratio":"0.00","oreb_pct":"0.000","dreb_pct":"0.000","treb_pct":"0.000","tm_tov_pct":"0.0","efg_pct":"0.000","ts_pct":"0.000","usg_pct":"0.000","pace":"91.14","pie":"0.091"},{"game_id":21200733,"team_id":1610612738,"player_id":203097,"opponent_id":1610612747,"period":"f","season":"2012","min":"4:58","off_rating":"100.0","def_rating":"132.5","ast_pct":"0.000","ast_tov":"0.000","ast_ratio":"0.00","oreb_pct":"0.000","dreb_pct":"0.000","treb_pct":"0.000","tm_tov_pct":"0.0","efg_pct":"0.500","ts_pct":"0.500","usg_pct":"0.167","pace":"98.19","pie":"-0.023"},{"game_id":21200794,"team_id":1610612738,"player_id":203097,"opponent_id":1610612743,"period":"f","season":"2012","min":"0:10","off_rating":"0.0","def_rating":"0.0","ast_pct":"0.000","ast_tov":"0.000","ast_ratio":"0.00","oreb_pct":"0.000","dreb_pct":"0.000","treb_pct":"0.000","tm_tov_pct":"0.0","efg_pct":"0.000","ts_pct":"0.000","usg_pct":"0.000","pace":"148.45","pie":"0.000"},{"game_id":21200807,"team_id":1610612738,"player_id":203097,"opponent_id":1610612747,"period":"f","season":"2012","min":"7:06","off_rating":"102.5","def_rating":"64.8","ast_pct":"0.000","ast_tov":"0.000","ast_ratio":"0.00","oreb_pct":"0.000","dreb_pct":"0.000","treb_pct":"0.000","tm_tov_pct":"0.0","efg_pct":"1.000","ts_pct":"0.532","usg_pct":"0.128","pace":"96.41","pie":"-0.026"},{"game_id":21200820,"team_id":1610612738,"player_id":203097,"opponent_id":1610612756,"period":"f","season":"2012","min":"3:42","off_rating":"74.0","def_rating":"83.3","ast_pct":"0.000","ast_tov":"0.000","ast_ratio":"0.00","oreb_pct":"0.000","dreb_pct":"0.200","treb_pct":"0.000","tm_tov_pct":"0.0","efg_pct":"0.000","ts_pct":"0.266","usg_pct":"0.215","pace":"90.55","pie":"0.000"},{"game_id":21201216,"team_id":1610612738,"player_id":203097,"opponent_id":1610612761,"period":"f","season":"2012","min":"17:26","off_rating":"98.3","def_rating":"115.1","ast_pct":"0.000","ast_tov":"0.000","ast_ratio":"0.00","oreb_pct":"0.000","dreb_pct":"0.125","treb_pct":"0.000","tm_tov_pct":"33.3","efg_pct":"0.500","ts_pct":"0.500","usg_pct":"0.087","pace":"83.87","pie":"-0.021"}]